{
  "model/models-dbg.js": 1733785985897,
  "i18n/i18n_en.properties": 1747978980881,
  "i18n/i18n.properties": 1747978968261,
  "manifest.json": 1750216226191,
  "controller/View1.controller.js": 1749964437076,
  "model/models.js": 1733785985897,
  "Component.js": 1733785985893,
  "i18n/i18n_fr.properties": 1748870837810,
  "model/models.js.map": 1750216226393,
  "controller/View1-dbg.controller.js": 1749964437076,
  "controller/View1.controller.js.map": 1750216226417,
  "Component-dbg.js": 1733785985893,
  "Component.js.map": 1750216226392,
  "Component-preload.js": 1750216226575,
  "Component-preload.js.map": 1750216226575,
  "view/View1.view.xml": 1749756688086,
  "images/MCKCAN1.jpg": 1749162065717,
  "css/style.css": 1740609139834,
  "index.html": 1733785985897
}