{
  "model/models.js": 1759258852137,
  "i18n/i18n_en.properties": 1759325670196,
  "i18n/i18n.properties": 1759325617464,
  "Component.js": 1759258852133,
  "model/formatter.js": 1759258852137,
  "controller/View1.controller.js": 1759516383206,
  "manifest.json": 1768245383468,
  "i18n/i18n_fr.properties": 1759258852133,
  "Component-dbg.js": 1759258852133,
  "Component.js.map": 1768245383755,
  "model/formatter-dbg.js": 1759258852137,
  "model/formatter.js.map": 1768245383758,
  "controller/View1-dbg.controller.js": 1759516383206,
  "controller/View1.controller.js.map": 1768245383794,
  "model/models-dbg.js": 1759258852137,
  "model/models.js.map": 1768245383755,
  "Component-preload.js": 1768245383899,
  "Component-preload.js.map": 1768245383899,
  "view/View1.view.xml": 1765581369556,
  "images/MCKCAN1.jpg": 1759258852137,
  "css/style.css": 1759258852133,
  "index.html": 1759258852137
}