{
  "Component-preload.js": 1756224279144,
  "i18n/i18n_en.properties": 1750026050119,
  "i18n/i18n_fr.properties": 1750026081563,
  "model/formatter.js": 1746022836522,
  "model/models.js": 1733785985921,
  "controller/View1.controller.js": 1749944155341,
  "manifest.json": 1756224278774,
  "Component.js": 1733785985921,
  "controller/View1-dbg.controller.js": 1749944155341,
  "controller/View1.controller.js.map": 1756224279030,
  "model/models-dbg.js": 1733785985921,
  "model/models.js.map": 1756224278999,
  "model/formatter-dbg.js": 1746022836522,
  "model/formatter.js.map": 1756224279010,
  "Component-dbg.js": 1733785985921,
  "Component.js.map": 1756224278999,
  "i18n/i18n.properties": 1750026039003,
  "Component-preload.js.map": 1756224279144,
  "view/View1.view.xml": 1750969740987,
  "images/MCKCAN1.jpg": 1749161933360,
  "css/style.css": 1740609182202,
  "index.html": 1753107716227
}