{
  "model/formatter.js.map": 1750026243559,
  "i18n/i18n_en.properties": 1745612022007,
  "i18n/i18n.properties": 1745612011763,
  "model/formatter.js": 1745606690767,
  "model/models.js": 1733785985937,
  "controller/View1.controller.js": 1749944802102,
  "manifest.json": 1750026243306,
  "Component.js": 1733785985933,
  "Component-dbg.js": 1733785985933,
  "Component.js.map": 1750026243541,
  "model/models-dbg.js": 1733785985937,
  "model/models.js.map": 1750026243548,
  "controller/View1-dbg.controller.js": 1749944802102,
  "controller/View1.controller.js.map": 1750026243613,
  "model/formatter-dbg.js": 1745606690767,
  "i18n/i18n_fr.properties": 1748870837810,
  "Component-preload.js": 1750026243785,
  "Component-preload.js.map": 1750026243786,
  "view/View1.view.xml": 1749756777606,
  "images/McKLogo.png": 1748894480819,
  "images/MCKCAN1.jpg": 1749161837031,
  "css/style.css": 1745606535434,
  "index.html": 1733785985937
}