{
  "view/View1.view.xml": 1765581605974,
  "i18n/i18n_fr.properties": 1759258852201,
  "i18n/i18n.properties": 1761060103016,
  "controller/View1.controller.js": 1765572031204,
  "model/formatter.js": 1759258852201,
  "model/models.js": 1759258852201,
  "manifest.json": 1768245508679,
  "Component.js": 1759258852201,
  "model/models-dbg.js": 1759258852201,
  "model/models.js.map": 1768245508933,
  "model/formatter-dbg.js": 1759258852201,
  "model/formatter.js.map": 1768245508938,
  "controller/View1-dbg.controller.js": 1765572031204,
  "controller/View1.controller.js.map": 1768245508992,
  "Component-dbg.js": 1759258852201,
  "Component.js.map": 1768245508917,
  "Component-preload.js": 1768245509107,
  "Component-preload.js.map": 1768245509107,
  "i18n/i18n_en.properties": 1761060093444,
  "images/MCKCAN1.jpg": 1759258852201,
  "css/style.css": 1759258852201,
  "index.html": 1759258852201
}